cbadenes_oscars/oscars.py
cbadenes_oscars/settings.py
cbadenes_oscars-0.0.1.dist-info/METADATA
cbadenes_oscars-0.0.1.dist-info/WHEEL
cbadenes_oscars-0.0.1.dist-info/licenses/LICENSE
cbadenes_oscars-0.0.1.dist-info/RECORD
