Metadata-Version: 2.1
Name: cbadenes_oscars
Version: 0.0.1
Summary: My ORM about movies and directors
Project-URL: Homepage, https://github.com/cbadenes/oscars
Project-URL: Bug Tracker, https://github.com/cbadenes/oscars/issues
Author-email: cbadenes <carlos.badenes@upm.es>
License:                                  Apache License
License-File: LICENSE
Classifier: License :: OSI Approved :: MIT License
Classifier: Operating System :: OS Independent
Classifier: Programming Language :: Python :: 3
Requires-Python: >=3.9
